Metadata-Version: 2.1
Name: cfkv
Version: 1.1.2
Summary: A Python wrapper for the Cloudflare KV Store API
Author: Paul Gardiner
Author-email: franticstone@gmail.com
License: MIT
Keywords: cloudflare,kv,cache,api,cloudflare workers
Classifier: Development Status :: 3 - Alpha
Classifier: Intended Audience :: Developers
Classifier: License :: OSI Approved :: MIT License
Classifier: Programming Language :: Python :: 3
License-File: LICENSE
